setup.py
multiprocess_wraps/__init__.py
multiprocess_wraps/base_multiprocess.py
multiprocess_wraps/multiprocess_enable_cuda.py
multiprocess_wraps/multiprocess_no_cuda.py
multiprocess_wraps.egg-info/PKG-INFO
multiprocess_wraps.egg-info/SOURCES.txt
multiprocess_wraps.egg-info/dependency_links.txt
multiprocess_wraps.egg-info/top_level.txt